{
    "AR_001": "http://rdfh.ch/0854/ZZzkuP4ZRruxELUCGRV4DQ",
    "A_01": "http://rdfh.ch/0854/zzf57p8sQAyAtirz8CaaUQ",
    "A_02": "http://rdfh.ch/0854/JjpDSKqJSH-m-KOEEJScrQ",
    "A_03": "http://rdfh.ch/0854/ioqjGfvzSP2a7aG6NvBgLQ",
    "A_04": "http://rdfh.ch/0854/xN-bkmxVRMKs54Xso-BHJA",
    "A_05": "http://rdfh.ch/0854/IjR5hSbGSK-WyFPpGI_Orw",
    "A_06": "http://rdfh.ch/0854/MpDHifr8Roy5AzyQ-AO8Qg",
    "A_07": "http://rdfh.ch/0854/NyZ_FhXJTxiS3oK15LLWFQ",
    "A_08": "http://rdfh.ch/0854/jfRBcvT6R8OcIIrSjsKdGQ",
    "A_09": "http://rdfh.ch/0854/IUbGWoMBTFa-j8dMzMbVfw",
    "A_10": "http://rdfh.ch/0854/0WRcJq4TS9iMEUAmHRerMg",
    "A_11": "http://rdfh.ch/0854/7MNT1WDNQTWTVRADCP9S0Q",
    "A_12": "http://rdfh.ch/0854/7-d_85t3QMCVgDONP6SpoA",
    "A_13": "http://rdfh.ch/0854/hLWelLHeRJizKn9F7KlY6w",
    "A_14": "http://rdfh.ch/0854/HhTLr7y7SemYD-lqULVGJA",
    "A_15": "http://rdfh.ch/0854/vqBRzSo-Q7qnvu8Qkf6o-A",
    "A_16": "http://rdfh.ch/0854/wjDnU-6XS1i6vaFowcBK3Q",
    "A_17": "http://rdfh.ch/0854/As5H1Qp-R02WXWUs9nySWg",
    "A_18": "http://rdfh.ch/0854/inxEB-Q2SCS2PgWfQb4d7A",
    "A_19": "http://rdfh.ch/0854/D-aFhEmeTdSZm1Dwsx8G9w",
    "A_20": "http://rdfh.ch/0854/H8KW3cMMSB2bTlHLylll7Q",
    "A_21": "http://rdfh.ch/0854/c36st5Y4RNS-oUCQUjnyZA",
    "A_22": "http://rdfh.ch/0854/nS_5uHBHSFiBsbFQgfo0Cw",
    "A_23": "http://rdfh.ch/0854/WF6iKb7pQeO_kfRcNAiDGA",
    "A_24": "http://rdfh.ch/0854/3l8b9-qdSA-6ZEBf8AqBFQ",
    "BCO_001": "http://rdfh.ch/0854/nykfJPsGSdi_JiDB2xWyQQ",
    "BCO_002": "http://rdfh.ch/0854/E2P3ZU4rQ6OWNs7OgMkYsw",
    "BCO_003": "http://rdfh.ch/0854/_ItIzNgLSYSBcrGTqwYicw",
    "BCO_004": "http://rdfh.ch/0854/i2j27sRgTVm8oQxlWQvEzQ",
    "BCO_005": "http://rdfh.ch/0854/qhDopJ3NQ3WDuWzHfdWKhQ",
    "BCO_006": "http://rdfh.ch/0854/pI-3zFtiShCtgZieuNnnXg",
    "BCO_007": "http://rdfh.ch/0854/eR4VwF5OSv6ums57Ht2ZgA",
    "BE_001": "http://rdfh.ch/0854/fvBLHpf3Qva_ozFOYnDuHQ",
    "BE_002": "http://rdfh.ch/0854/QOIOSlF6TuKV3tu0VIlqHw",
    "BE_003": "http://rdfh.ch/0854/3vLxarBYTYOyTVZer_KO9A",
    "BE_004": "http://rdfh.ch/0854/rQ2Ao1kfRsitYO_jlnbjbw",
    "BE_005": "http://rdfh.ch/0854/6D7tCDqHSY-fUfgRK9U5dQ",
    "BCH_001": "http://rdfh.ch/0854/3JWNUUvySBCMw2FRFxN8Cw",
    "BCH_015": "http://rdfh.ch/0854/aN6ToQRqTP2Syp2I8bt5xQ",
    "BCH_016": "http://rdfh.ch/0854/bmYySZ6sRUmmu3EQfMPKGQ",
    "BCH_029": "http://rdfh.ch/0854/ji35v79xS9OxmRh_VZhKcg",
    "CH_016": "http://rdfh.ch/0854/KDpKmJVGTmiaaZZJlkyeyQ",
    "CH_019": "http://rdfh.ch/0854/ZRsBljGATTaG_tOgpVjeFQ",
    "CH_020": "http://rdfh.ch/0854/MqaumSzrRQyCJRqk-akQYw",
    "CH_021": "http://rdfh.ch/0854/t3k5CORNSIWPw3f4-JrlDA",
    "CH_022": "http://rdfh.ch/0854/ib1g7Vd9QQmPSc9mRgnU9g",
    "CH_023": "http://rdfh.ch/0854/srC05X-sTJOpqcY3ieEX_Q",
    "CH_024": "http://rdfh.ch/0854/sAvURLSlQYCoTefIVzm6fQ",
    "CH_025": "http://rdfh.ch/0854/U7cNiXQsT3im3TbdW81rzQ",
    "CH_029": "http://rdfh.ch/0854/WjKr-Nx5RESaDm967LlvEw",
    "CH_034": "http://rdfh.ch/0854/u7pI1yU_TTi1EI-Dze6iEw",
    "CH_051": "http://rdfh.ch/0854/tnmYLzeiQ9Oygnw3QaUCjA",
    "DOC_001": "http://rdfh.ch/0854/GQh4BUD0SpG3coopGF_N-Q",
    "DOC_002": "http://rdfh.ch/0854/9YQW4qetR86adbV7QzhNIg",
    "DOC_003": "http://rdfh.ch/0854/IEomEs8NRdeqK1LzKmqyUg",
    "DOC_004": "http://rdfh.ch/0854/oussq0bKS0C95_hzYdFspw",
    "EV_025": "http://rdfh.ch/0854/4SJJhHkfRiqyLxWnX5UJpA",
    "EV_040": "http://rdfh.ch/0854/ISqhV2sESf2RJYhLvoZErg",
    "EV_041": "http://rdfh.ch/0854/wUc1yvtkRZ6xK-DRFOVacw",
    "EV_042": "http://rdfh.ch/0854/2f4xSo-dTdKSmHvXTFTfTw",
    "EV_043": "http://rdfh.ch/0854/fiRQ4BSeSEqoXG7t23JPtg",
    "EV_044": "http://rdfh.ch/0854/4a2dl50WRp2HkdhxeiI3bA",
    "EV_045": "http://rdfh.ch/0854/tpHstxGFRMqILDJzpP_yfA",
    "EV_046": "http://rdfh.ch/0854/h_aeRMWYTWq_du_GIATIag",
    "EV_047": "http://rdfh.ch/0854/ah8cS-hyT8Odfe8GvWyfOA",
    "EV_048": "http://rdfh.ch/0854/lyyrJB7sQemVI859TisN7Q",
    "EV_049": "http://rdfh.ch/0854/H3pg-W7FRkCv0vFSXri9Pg",
    "EV_050": "http://rdfh.ch/0854/VVVTWlLpS-OTa7d0-7w55g",
    "EV_051": "http://rdfh.ch/0854/rxqMG5D_SPGvT9n2rxCuNg",
    "L_032": "http://rdfh.ch/0854/HLPXnApjQ-S3ZZl_P73w0Q",
    "L_010": "http://rdfh.ch/0854/XelfmugERj-4hNfDj9XEmA",
    "L_009": "http://rdfh.ch/0854/Xj-Mn0VnTEGdOR3tgsIDBA",
    "L_006": "http://rdfh.ch/0854/fWqv3iYoQWm7f1D9SBz4YA",
    "L_031": "http://rdfh.ch/0854/Y1fB7XlgSkCGoiSGyGvw0w",
    "L_001": "http://rdfh.ch/0854/8QexDndkQbOd0EK1fO9N2A",
    "L_005": "http://rdfh.ch/0854/BQpXCZ_iTDm-EtNYDlXOCw",
    "L_015": "http://rdfh.ch/0854/4-drydJ8Ts2DMQH4cBXjxw",
    "MAT_001": "http://rdfh.ch/0854/awgiGGtASTW3WKZw8ZxFwA",
    "MAT_002": "http://rdfh.ch/0854/spaqyh1_RB2BO0IR5QhlVQ",
    "MAT_003": "http://rdfh.ch/0854/VJgkrO0dRECm4rNrAbe4LQ",
    "MAT_004": "http://rdfh.ch/0854/YjaJ9Nf4Q2CQeFgXFu2vuQ",
    "MAT_005": "http://rdfh.ch/0854/kQT_UGzTSlC7kS8tBmta_g",
    "MAT_006": "http://rdfh.ch/0854/Kf38odyURumbGQiBaSCDMg",
    "MAT_007": "http://rdfh.ch/0854/u0fcx9vRRcOYBPoLUp7JSA",
    "MAT_008": "http://rdfh.ch/0854/zY9ISnAwRIunioxybr2gRA",
    "MAT_009": "http://rdfh.ch/0854/cfFh5-HDQIa5kGiiosJZ0A",
    "MAT_010": "http://rdfh.ch/0854/KCDAL1J1TxuNAXEgqERZSQ",
    "MAT_011": "http://rdfh.ch/0854/IPdgbFRLRICJJAQ1F6Irfg",
    "MAT_012": "http://rdfh.ch/0854/qjBQXte8To6Kt7GZO_r_zw",
    "MAT_013": "http://rdfh.ch/0854/UaW1dUPhR6Wa_w-W6sE0fQ",
    "MAT_014": "http://rdfh.ch/0854/P931xahVSyWLrPX265Qjcg",
    "MAT_015": "http://rdfh.ch/0854/xnUFjokiT4uWqRy2OXimdg",
    "MAT_016": "http://rdfh.ch/0854/mH2lez4nTeC5odxR99yG1w",
    "MAT_017": "http://rdfh.ch/0854/9Z1zoU74Sp-B_u7NyoCB2A",
    "MAT_018": "http://rdfh.ch/0854/Z7lX1Wx8TvmDm_STm8Hfdg",
    "MAT_019": "http://rdfh.ch/0854/9FTksuWyRLmInkBJwYDeXw",
    "MAT_020": "http://rdfh.ch/0854/ndUUFNccRSCmNZH3btJcfg",
    "MAT_021": "http://rdfh.ch/0854/XiDbNJ4XS46dy4hHPsvyTQ",
    "MAT_022": "http://rdfh.ch/0854/gQhCZl_CQt6XRPqyP1PAqw",
    "MAT_023": "http://rdfh.ch/0854/9ah5BLzZS96NmVP478t7CA",
    "MAT_024": "http://rdfh.ch/0854/r78fNac7SyaM9pMKT_cGxQ",
    "MAT_025": "http://rdfh.ch/0854/gnLRU1w_TaGSEAk_hiF8XQ",
    "MAT_026": "http://rdfh.ch/0854/6Xb_DKDHQgeRk8wIRiGYjQ",
    "MAT_027": "http://rdfh.ch/0854/oeNBgPEVSdymYVlMmoCJzQ",
    "MAT_028": "http://rdfh.ch/0854/dgSAkD_GRlGoXoqG9nVthQ",
    "MAT_029": "http://rdfh.ch/0854/z2b_eKOjTIqGtRfk5epO7w",
    "MAT_030": "http://rdfh.ch/0854/Xmxf2F84QgCuRbK1G8be1w",
    "MAT_031": "http://rdfh.ch/0854/5_5CXpbDQwKP_AeeSRpFqQ",
    "MAT_032": "http://rdfh.ch/0854/xUzopxrBQy6NP4Ri-LVagA",
    "MAT_033": "http://rdfh.ch/0854/3miPz6PxTI-nJOIGWrDIGQ",
    "MAT_034": "http://rdfh.ch/0854/PEJvRTn5RIq5QaQ5tItjKQ",
    "V_01": "http://rdfh.ch/0854/hjqpcjJhRWaUWcW_VNyoeQ",
    "BCH_014": "http://rdfh.ch/0854/9TLPj9TIQk6NG5n09aW90g",
    "VIS_001": "http://rdfh.ch/0854/mrKodacPTSCQrwa8m3Dy4A",
    "VIS_002": "http://rdfh.ch/0854/20Y8U6bLS7Oe8IJjd5FJjg",
    "VIS_003": "http://rdfh.ch/0854/hf9IKkuHRc2JTqudd-fRpw",
    "AUS_001": "http://rdfh.ch/0854/-aDXTB2yT_SVGXfHLQXwSQ",
    "AUS_002": "http://rdfh.ch/0854/rGewotPEQ6OnovRMriJ0Cg",
    "AUS_003": "http://rdfh.ch/0854/cthpCQoHQ_uAoHCUtySTzQ",
    "AUS_004": "http://rdfh.ch/0854/CAubvUuqR2iq-qqe8juUEA",
    "AUS_005": "http://rdfh.ch/0854/Y3K72D92TnuvGfmGzWuMMw",
    "AUS_007": "http://rdfh.ch/0854/YYtKxmc6T2SxhG923_j38g",
    "AUS_008": "http://rdfh.ch/0854/f6OjVwvYRniqqS2XxS2IDQ",
    "AUS_010": "http://rdfh.ch/0854/JlY7F1GUTSKqMebmJ-UjbA",
    "I_021": "http://rdfh.ch/0854/ljjDTXU-SNygfkK-nllBEQ",
    "CH_033": "http://rdfh.ch/0854/1znq3MTgTtmOMMbSu_klmg",
    "L_020": "http://rdfh.ch/0854/6-pN23OzRSa1OQNsuc53sQ",
    "BK_001": "http://rdfh.ch/0854/6fGZ4RE3Ruy4G4KtyYH0lQ",
    "I_009": "http://rdfh.ch/0854/GNr1TuDUTTOtnfjlmdccPA",
    "I_032": "http://rdfh.ch/0854/yk9T8YFmSJuNPlv2iR6e8w",
    "I_008": "http://rdfh.ch/0854/E-M8PeaPS2WFrC74I9dZbQ",
    "I_003": "http://rdfh.ch/0854/NM2AkBnUSTGBrIzcCHJrRQ",
    "I_005": "http://rdfh.ch/0854/ZBJhKpakTkWodEMx7E88cw",
    "I_030": "http://rdfh.ch/0854/fNAivI-EQA2HFnxSVvW5eQ",
    "I_004": "http://rdfh.ch/0854/ARFN82w1Rmup8Shh-61ctg",
    "I_022": "http://rdfh.ch/0854/rV7LTsjeQxyaYCu2jbxIhw",
    "I_011": "http://rdfh.ch/0854/i3GjI2CnRNe6KFK44Ca9RQ",
    "I_025": "http://rdfh.ch/0854/H4fIYr10SQKx214rk8oa8g",
    "I_007": "http://rdfh.ch/0854/-BXmqIWZSZ-rCkFkFyUnhQ",
    "I_040": "http://rdfh.ch/0854/ZyRsBcUTQWOh-xHihADb0g",
    "I_012": "http://rdfh.ch/0854/A9k-ABKKSWeBX4zbjYYS8Q",
    "I_013": "http://rdfh.ch/0854/uhc7XKJmTRm_TNDFrocyEQ",
    "I_028": "http://rdfh.ch/0854/3YRxS1LhTyuuxy0TD8_j9A",
    "I_042": "http://rdfh.ch/0854/QDPgjKrBTO--ik4Z_ecn8Q",
    "I_015": "http://rdfh.ch/0854/n_BXqHhXQlSiYAQg6XpzzQ",
    "I_024": "http://rdfh.ch/0854/XiqSe8r_Tu62WhndJmbOWg",
    "I_023": "http://rdfh.ch/0854/cYQF8-h3TVSch9sIZ37CYA",
    "I_027": "http://rdfh.ch/0854/G9ivMG5CRJCKLy2TsCld6Q",
    "I_031": "http://rdfh.ch/0854/_d7mWdOTQlqg1FeJdxp6Dw",
    "I_019": "http://rdfh.ch/0854/KHX4ffGzTxe3pgDhQ-q2Hw",
    "I_018": "http://rdfh.ch/0854/rMVfBsYTREK6ze7RA9KAgg",
    "I_016": "http://rdfh.ch/0854/feOn2DRgSAqYYl-GQ4RLHA",
    "I_017": "http://rdfh.ch/0854/Lz-2wQtqQ4iAqNLeFNt3Cg",
    "I_020": "http://rdfh.ch/0854/-_3DPdSAT7qLvGjQsNDK4A",
    "I_033": "http://rdfh.ch/0854/9l6inGfySiuP-5b4LSFWSA",
    "I_039": "http://rdfh.ch/0854/JLhXMIAFRfmCj79hkev_vA",
    "I_038": "http://rdfh.ch/0854/bwDXEtBMTEubrfqaxKt5FA",
    "I_026": "http://rdfh.ch/0854/mfp3j5euTICwS-ZMxejkiw",
    "I_001": "http://rdfh.ch/0854/Hr6i_d0lSli8aFsjJkLNvw",
    "I_041": "http://rdfh.ch/0854/A4MW-wyWQHurf9maUW33uQ",
    "I_036": "http://rdfh.ch/0854/AQYMteqTS6CMvJatfiYI-Q",
    "I_035": "http://rdfh.ch/0854/8MX1LfkZTKeDHujsOXWRGQ",
    "I_034": "http://rdfh.ch/0854/RHVGy2rfRie9pubsLysaNg",
    "I_010": "http://rdfh.ch/0854/0nAjCLoEQBCLAhqOJsJTBA",
    "I_029": "http://rdfh.ch/0854/sOcvKsFkRNigLsFBPxf9eA",
    "I_014": "http://rdfh.ch/0854/obKfy_62SLK8sDfNmBOqhg",
    "I_037": "http://rdfh.ch/0854/zowdoAhvRQKvCpeeO82Mng",
    "I_002": "http://rdfh.ch/0854/AyRh870bRoCuYzQpxUmTGg",
    "I_006": "http://rdfh.ch/0854/kxetgLYrSLSpdczzRRLcTg",
    "CH_002": "http://rdfh.ch/0854/vdq5PMSQQtmlFBq33ilLaw",
    "CH_003": "http://rdfh.ch/0854/aNFI0LkoROKeE0YAVzWCCA",
    "CH_005": "http://rdfh.ch/0854/PfvQxzAITzuBOlpmuBtjgg",
    "CH_006": "http://rdfh.ch/0854/48lVo59NQluAKAmyBzuBeQ",
    "CH_008": "http://rdfh.ch/0854/lUq2zZqLTL2fbeRF6a1B_g",
    "CH_009": "http://rdfh.ch/0854/A6RhqtfXThis_rhGeAV3PQ",
    "CH_010": "http://rdfh.ch/0854/6UnGN122ST2OrohvFyjN-g",
    "CH_014": "http://rdfh.ch/0854/8lWey64MQgGQNKk9KQWgmA",
    "CH_015": "http://rdfh.ch/0854/UL6S4TwbRX-PGF6zN6N1yQ",
    "CH_017": "http://rdfh.ch/0854/F4J-875MRjKoLUi-Y5m8jQ",
    "CH_018": "http://rdfh.ch/0854/NJitRoy3TNarbCWJdfMzXw",
    "CH_027": "http://rdfh.ch/0854/bij4ffi4SEiSXboqkgitwg",
    "CH_028": "http://rdfh.ch/0854/AZ4sFW_NQXCgVOQs5XUSvA",
    "CH_031": "http://rdfh.ch/0854/ay7O_3oqTwGDflaQrIJSqQ",
    "CH_032": "http://rdfh.ch/0854/y-xQBM8IQ06r5411n7w_jw",
    "CH_035": "http://rdfh.ch/0854/qiD0F02rQgmvqoX791vsXQ",
    "CH_036": "http://rdfh.ch/0854/eY8g-DJBTq62MMoLE2u4IA",
    "CH_037": "http://rdfh.ch/0854/3ubS3Gz-QxyQJhHTTpB7kw",
    "CH_038": "http://rdfh.ch/0854/Lqx2D-5zTVSuJSiYrRabqg",
    "CH_039": "http://rdfh.ch/0854/b6ADlxSTTDOmKTl_U2AnDQ",
    "L_014": "http://rdfh.ch/0854/We_aj1fZSoGBgmTg-q_eAg",
    "L_021": "http://rdfh.ch/0854/qJIZ3cMhTOelW7FXa0UskA",
    "L_016": "http://rdfh.ch/0854/8NVVYRmOSYKQTD6M-9GmGA",
    "L_003": "http://rdfh.ch/0854/r2IsBcAeQq63lHq7x73GdA",
    "L_011": "http://rdfh.ch/0854/MQqxOFcSQzyErbdOrapxOw",
    "L_007": "http://rdfh.ch/0854/n61HmN15SbaLhPe8BDOkyg",
    "L_018": "http://rdfh.ch/0854/yt0vIkhpSX6QqZVVpX1bVA",
    "L_008": "http://rdfh.ch/0854/zRbIVmWCQKSxjhoOfbH8Dw",
    "L_022": "http://rdfh.ch/0854/HF_hynfTRcGFDrIXFM8KTg",
    "L_013": "http://rdfh.ch/0854/t1DNNV96QVa0z5hMfu6nHg",
    "L_002": "http://rdfh.ch/0854/bJ27XQIPRNW-eyIGgpBhWg",
    "L_004": "http://rdfh.ch/0854/_Xo4se19SuWG0wmLa-78AQ",
    "R_001": "http://rdfh.ch/0854/MupXOnHiQBeAyMUfNPRqfQ",
    "R_002": "http://rdfh.ch/0854/7nqfQ_ZwRqqDReJqmRDOZw",
    "R_003": "http://rdfh.ch/0854/SqA--PoLSFuqMlGVPhE9Xw",
    "R_004": "http://rdfh.ch/0854/MWfnHB7DRC6bPxwhVQSf-Q",
    "R_005": "http://rdfh.ch/0854/COK_KMEjShOTuIG3IfceuA",
    "R_006": "http://rdfh.ch/0854/8WuW8fcgQZK93fUH3pONpA",
    "R_007": "http://rdfh.ch/0854/bbQgxn7aSBqzunCf0d90Ow",
    "EV_011": "http://rdfh.ch/0854/e2N17PYORbWbKXoVj4sQpg",
    "BCH_012": "http://rdfh.ch/0854/-DaPkTs3QiGQeyMAFQie6Q",
    "BK_002": "http://rdfh.ch/0854/VLbgeOwLR62F-EyoZHqtnQ",
    "I_068": "http://rdfh.ch/0854/pyGzhQkjRIequXFwHjcXnw",
    "I_087": "http://rdfh.ch/0854/sdAh9bH5SaqIQmZP-DhANA",
    "I_055": "http://rdfh.ch/0854/H0oadssMSI6Zr1ky_31XZA",
    "I_053": "http://rdfh.ch/0854/m8xP_RRWQMOXiqGaj94UTg",
    "I_061": "http://rdfh.ch/0854/Qwce0wzrRyqCkswRjvGw3w",
    "I_060": "http://rdfh.ch/0854/6jVAXvDTSSuu-QdBO7u8Sg",
    "I_047": "http://rdfh.ch/0854/Xe8jyImaRz-Fsh1N0IiJFQ",
    "I_082": "http://rdfh.ch/0854/rUWg4xkWT46-HH1i71hSqQ",
    "I_046": "http://rdfh.ch/0854/FsNNFmiEQ1yrbmf33h1U-w",
    "I_078": "http://rdfh.ch/0854/w0Jg3JvASN-qnXBSBYTmfQ",
    "I_070": "http://rdfh.ch/0854/O6ZoilLnT5C45R7875jq_w",
    "I_084": "http://rdfh.ch/0854/2lhORDXXTfi19yo7iOXtMw",
    "I_092": "http://rdfh.ch/0854/MZ4j_W3CSbO_hfj8OVGyrQ",
    "I_049": "http://rdfh.ch/0854/N2CV4FhIRjOYqfIZBf_PjA",
    "I_089": "http://rdfh.ch/0854/LemhW8I0Qjyi3fsKNNyjnQ",
    "I_079": "http://rdfh.ch/0854/jgVhVZ3WRV6lLUGV9V8Umw",
    "I_071": "http://rdfh.ch/0854/Yg97dlonRESxl6LhXIngOw",
    "I_091": "http://rdfh.ch/0854/MRTVQwfZRt-hsUx3rSbUIA",
    "I_090": "http://rdfh.ch/0854/yTf8Zz-DQpmn5EybjLpXcg",
    "I_056": "http://rdfh.ch/0854/sspet212Q5O2aln9joxKWw",
    "I_045": "http://rdfh.ch/0854/fog_Et1UTkCtQvEGTw5-fQ",
    "I_044": "http://rdfh.ch/0854/fdQksDEGT2-xMJHx3yZNUw",
    "I_059": "http://rdfh.ch/0854/poX-CmIeRwGoRzrIpquCqA",
    "I_054": "http://rdfh.ch/0854/vYONa4RgRjuRLvsFylEqgw",
    "I_048": "http://rdfh.ch/0854/IzwKOjuXS8-oam_rq6hbKg",
    "I_076": "http://rdfh.ch/0854/ob3fMdQcQcKPzymzxBNHgQ",
    "I_077": "http://rdfh.ch/0854/DtaEpysJTU6c8F9JIRFJag",
    "I_069": "http://rdfh.ch/0854/yl7vGlCaTea9yn7PBMCVEQ",
    "I_072": "http://rdfh.ch/0854/S83Q_ALsTxaZ6VcTRAvfag",
    "I_074": "http://rdfh.ch/0854/xbG1XktbTP-s023bxglUhw",
    "I_073": "http://rdfh.ch/0854/QzMElWtYSn681X5VSba7TQ",
    "I_051": "http://rdfh.ch/0854/8W-GKHtITJCN__DFSnq-Pg",
    "I_088": "http://rdfh.ch/0854/PIWJNtHURi66QmsbNMucSg",
    "I_065": "http://rdfh.ch/0854/OkrRGqbjTjedAFt_g2K6Eg",
    "I_080": "http://rdfh.ch/0854/Ia47thH9Qxym3WShi8b0vA",
    "I_085": "http://rdfh.ch/0854/WCZaQcbJR0GNK8wTbkscdA",
    "I_086": "http://rdfh.ch/0854/OMqW0XzRT3u41LAytvWpxg",
    "I_057": "http://rdfh.ch/0854/Sb7UQCkaQ82-PjxPR-JV4A",
    "I_058": "http://rdfh.ch/0854/mO9HYoViTcmH9TEO4gt0og",
    "I_050": "http://rdfh.ch/0854/M6Hu8NhdQx2ce6PveDQLzQ",
    "I_052": "http://rdfh.ch/0854/T_oI3OLYRUyZ-5vjSgbuww",
    "I_067": "http://rdfh.ch/0854/ihROCLS3T7e_XfqQ9OgdcQ",
    "I_066": "http://rdfh.ch/0854/bsN9pXjkQC-8rGilDZmd8Q",
    "I_064": "http://rdfh.ch/0854/l7oH7qUCRqq4M5OLZ5pTOw",
    "I_063": "http://rdfh.ch/0854/Nh3ybdnyS1S84NsFEQhlKQ",
    "I_062": "http://rdfh.ch/0854/ZSrL-XvuTPqWmkcgPb1IKw",
    "I_075": "http://rdfh.ch/0854/iddACv3HTFeBEo7JjM-7Lg",
    "I_081": "http://rdfh.ch/0854/F9mraRAFTfmNGG4FDyNkdQ",
    "I_043": "http://rdfh.ch/0854/VhdH9_0cSK-ofIX1Y0_0Tg",
    "I_083": "http://rdfh.ch/0854/B9eSmRG1S4WQJJtzDbVGBg",
    "CH_001": "http://rdfh.ch/0854/D3eLiTCbRjW_uedY3CIeIA",
    "CH_004": "http://rdfh.ch/0854/fc3Q3OzGSli2QJgZipNYkw",
    "CH_007": "http://rdfh.ch/0854/MURwCrVBTZ6qNSXNLEemoQ",
    "CH_011": "http://rdfh.ch/0854/MsDRojIGQBOBAg3YQ5uqjA",
    "CH_012": "http://rdfh.ch/0854/qioslSs4RpKYqGQfPooluw",
    "CH_013": "http://rdfh.ch/0854/Et04-MehQiO3kX2Idihzrw",
    "CH_026": "http://rdfh.ch/0854/Cnn6gcf6Q_iOV_pw2IaKIw",
    "CH_030": "http://rdfh.ch/0854/NAwL5d5_T7GrnXTZ-7a3kw",
    "CH_040": "http://rdfh.ch/0854/oHSDGk8wTDeTFp3u8ehTKg",
    "CH_041": "http://rdfh.ch/0854/CC2sugurQ4SMr05RFPYuHw",
    "CH_042": "http://rdfh.ch/0854/WMw7cHalQGKfNh5OWG4iQA",
    "CH_043": "http://rdfh.ch/0854/aZpNZtEcSQq_mmotzeDYew",
    "CH_044": "http://rdfh.ch/0854/v7ITcq4yTqqEujQhhpRyLg",
    "CH_045": "http://rdfh.ch/0854/phFP-FB1Qna6VgzAR2TVJA",
    "CH_046": "http://rdfh.ch/0854/zyg-VQb9TTe-fkV_1bh8Jg",
    "CH_047": "http://rdfh.ch/0854/zWxhu0oOT0KeERdH3vhCBg",
    "CH_048": "http://rdfh.ch/0854/IH4tMBC2TD-sNQ8x11wGsg",
    "CH_049": "http://rdfh.ch/0854/JX8VpH68Q7invEBqwFis8w",
    "CH_050": "http://rdfh.ch/0854/vQ-fRB5dQgydD4A_yoETng",
    "CH_052": "http://rdfh.ch/0854/eyTY2qItTeWEWbp8IF8WDQ",
    "CH_053": "http://rdfh.ch/0854/WBpl9Py3ScGyMxAqzUIBug",
    "CH_054": "http://rdfh.ch/0854/hxUlETrESOGuBSyl9ke55A",
    "L_019": "http://rdfh.ch/0854/ouFbvxZKRvOfut9rdvwV7Q",
    "L_024": "http://rdfh.ch/0854/8zEbFin6RLOTNDUXTpkygA",
    "L_012": "http://rdfh.ch/0854/WLZ5Ah8iQyC7N6DgAh-8jA",
    "L_025": "http://rdfh.ch/0854/0Lt-hksQSgWkFLbIo505bQ",
    "L_028": "http://rdfh.ch/0854/DdsP5AekTWOASJP9vK6PYA",
    "L_029": "http://rdfh.ch/0854/q0kkUfmGSi6suzkNkM7sCw",
    "L_023": "http://rdfh.ch/0854/bi5XRdqCRC22BWAfGNTOXA",
    "L_026": "http://rdfh.ch/0854/MbGcOJf9RIOlK3Y5x2Zc9Q",
    "L_030": "http://rdfh.ch/0854/3d1hav4kQ7mkKAjE3jQWxw",
    "L_017": "http://rdfh.ch/0854/Kmm540IWTwC6qsBYmAvP9g",
    "L_027": "http://rdfh.ch/0854/qPngJCF8RuStiAOKrx__Cg",
    "EV_003": "http://rdfh.ch/0854/9MYWbtZOQBmwLOTDxgyLOw",
    "EV_004": "http://rdfh.ch/0854/vqUxGVmbQMi-KmUBGlg0OQ",
    "EV_005": "http://rdfh.ch/0854/ShpH1ys6TaWDgmLbtqMW4A",
    "EV_006": "http://rdfh.ch/0854/SZHiFS6rSDe1FOsexuO31Q",
    "EV_007": "http://rdfh.ch/0854/RguWMthnQnCqLRvsr3kY-w",
    "EV_008": "http://rdfh.ch/0854/8T8QUd0DS8KzFMTfZBMLiA",
    "EV_009": "http://rdfh.ch/0854/Ohs0FTfOSBi4taZ8Z6RDjg",
    "EV_010": "http://rdfh.ch/0854/RuX1w6pQQO-WS8OpIxi60g",
    "EV_012": "http://rdfh.ch/0854/UNZMOEypTzSEq3HnChEpLg",
    "EV_013": "http://rdfh.ch/0854/6Ej8znOLQGWjZYgWg7XBsw",
    "EV_014": "http://rdfh.ch/0854/OcbwKUCsQKyJBAKEplF4JA",
    "EV_015": "http://rdfh.ch/0854/r5B9leizT1aLK5dJkwf7Bg",
    "EV_016": "http://rdfh.ch/0854/7pvL62CESo-DVn6O2cjMNQ",
    "EV_017": "http://rdfh.ch/0854/rUoWhP6jRxymLbiKXezahg",
    "EV_018": "http://rdfh.ch/0854/qWz_Q4aUTYeWz7lcC1cNIg",
    "EV_019": "http://rdfh.ch/0854/PPs07p2oT5mpWYq6y4BE8g",
    "EV_020": "http://rdfh.ch/0854/WYBDQUmzRNW33GP9H2XJew",
    "EV_021": "http://rdfh.ch/0854/kVK2SltxTpy2V9bqX5_rtw",
    "EV_022": "http://rdfh.ch/0854/V4tgkQYcQry4PPywoGE7-A",
    "EV_023": "http://rdfh.ch/0854/IpzIzdvqTdOEYseYPrWZ_w",
    "EV_024": "http://rdfh.ch/0854/87jJ6qLKRHCikgCbFEGoZw",
    "EV_026": "http://rdfh.ch/0854/WSvtzawITkGj2wT2yGJZLQ",
    "EV_027": "http://rdfh.ch/0854/ZrTfNzs4RvaRBON8MgwbYA",
    "EV_028": "http://rdfh.ch/0854/DAIibeawRDSjo8TDFuQf8Q",
    "EV_029": "http://rdfh.ch/0854/C6_9URj0QkeCz29kOczWtg",
    "EV_030": "http://rdfh.ch/0854/rt2JGfq0STWz7s2bTV2A7Q",
    "EV_031": "http://rdfh.ch/0854/yuAxwvSxQNmLqAXc2J-0rA",
    "EV_032": "http://rdfh.ch/0854/3Plj1Mv1QAi2NjV72kO7Gw",
    "EV_033": "http://rdfh.ch/0854/WjVK3eglT6SFRGt-Xush9Q",
    "EV_034": "http://rdfh.ch/0854/Nr8Ikr3VRHm-hnS_LWuPRA",
    "EV_035": "http://rdfh.ch/0854/0NWLgbZRSrKlUMuppLH1LQ",
    "EV_036": "http://rdfh.ch/0854/saoHx3oVSl-gC9sgyMFdlQ",
    "EV_037": "http://rdfh.ch/0854/SYlswEIETeKvU9HkVCDMQg",
    "EV_038": "http://rdfh.ch/0854/WBtai1ebSXKs1hsl526Uag",
    "EV_039": "http://rdfh.ch/0854/xgGLDu9BSbSiiv6NjXMABg",
    "EV_001": "http://rdfh.ch/0854/SgTWyAJqQuuE5RUU055wJQ",
    "EV_002": "http://rdfh.ch/0854/Z9lJWyKqR2-4GF4P55Us_A",
    "BCH_002": "http://rdfh.ch/0854/P1NkiX9YRlqqsJo3Bu_nlQ",
    "BCH_003": "http://rdfh.ch/0854/6asFQy71ShmMIZlkaEjMdQ",
    "BCH_004": "http://rdfh.ch/0854/hCjFrm_nSF61FEnvp44e0Q",
    "BCH_005": "http://rdfh.ch/0854/ViPh3295QhqEktqay_YwFg",
    "BCH_006": "http://rdfh.ch/0854/8qtSGElcTSeBGDiBEXOGNA",
    "BCH_007": "http://rdfh.ch/0854/36q1CUgSRYar1A5X7tmwfQ",
    "BCH_008": "http://rdfh.ch/0854/zyZlOr9kQeq-0VjzipARqg",
    "BCH_009": "http://rdfh.ch/0854/XFGqxjSYTB-jdfx8LpvHcQ",
    "BCH_010": "http://rdfh.ch/0854/2vK4K22pSgeGPiKPyRGnMA",
    "BCH_011": "http://rdfh.ch/0854/H3FDUcs8TYannUnEa-hpPQ",
    "BCH_013": "http://rdfh.ch/0854/d6GtbbVEQr6et2ODp0uQIA",
    "BCH_017": "http://rdfh.ch/0854/rlTflDXDQseiRF84KdyATQ",
    "BCH_018": "http://rdfh.ch/0854/xlsK9ZepQvOo6d55idjKFg",
    "BCH_019": "http://rdfh.ch/0854/4UW-XmLER2ueBHQ2gTySXQ",
    "BCH_020": "http://rdfh.ch/0854/XtvGGdA2QhCYAguiDR0vow",
    "BCH_021": "http://rdfh.ch/0854/mZFMkTtESgaNt_7KHns1-A",
    "BCH_022": "http://rdfh.ch/0854/oEVqNYNZRXmICtZsl94J0w",
    "BCH_023": "http://rdfh.ch/0854/O-31TJ7PSuqXxjxxRAVmgQ",
    "BCH_024": "http://rdfh.ch/0854/f6owdoqkRraOFI4rrjbjwQ",
    "BCH_025": "http://rdfh.ch/0854/6aBWvJ9YT7i8rRJ9yelhnA",
    "BCH_026": "http://rdfh.ch/0854/CAMrch0gS8meGJrYGKiIYg",
    "BCH_027": "http://rdfh.ch/0854/WRqP6THaRt25JFNUCzaEPw",
    "BCH_028": "http://rdfh.ch/0854/_2-9Hw7wSfWPb7RwcLVV9w",
    "AUS_009": "http://rdfh.ch/0854/LJ-HyfxlS--Bzrcr-QG9mg",
    "AUS_006": "http://rdfh.ch/0854/5DBEXodNT4yAbA9-7wlgmQ"
}